clickpesa/__init__.py
clickpesa/client.py
clickpesa/exceptions.py
clickpesa/models.py
clickpesa-1.0.0.dist-info/METADATA
clickpesa-1.0.0.dist-info/WHEEL
clickpesa-1.0.0.dist-info/licenses/LICENSE
clickpesa-1.0.0.dist-info/RECORD
