Metadata-Version: 2.4
Name: clickpesa
Version: 1.0.0
Summary: A Python library for integrating with ClickPesa payment gateway API
Project-URL: Homepage, https://github.com/AvicennaJr/clickpesa
Project-URL: Repository, https://github.com/AvicennaJr/clickpesa
Project-URL: Documentation, https://github.com/AvicennaJr/clickpesa#readme
Project-URL: Bug Tracker, https://github.com/AvicennaJr/clickpesa/issues
Author-email: Fuad Habib <info@fuadhabib.xyz>
License-Expression: MIT
License-File: LICENSE
Keywords: api,clickpesa,mobile-money,payment,payments,tanzania,ussd
Classifier: Development Status :: 4 - Beta
Classifier: Intended Audience :: Developers
Classifier: License :: OSI Approved :: MIT License
Classifier: Operating System :: OS Independent
Classifier: Programming Language :: Python :: 3.8
Classifier: Programming Language :: Python :: 3.9
Classifier: Programming Language :: Python :: 3.10
Classifier: Programming Language :: Python :: 3.11
Classifier: Programming Language :: Python :: 3.12
Classifier: Programming Language :: Python :: 3.13
Classifier: Topic :: Office/Business :: Financial :: Point-Of-Sale
Classifier: Topic :: Software Development :: Libraries :: Python Modules
Classifier: Typing :: Typed
Requires-Python: >=3.8
Requires-Dist: requests>=2.25.0
Requires-Dist: typing-extensions>=4.0.0
Provides-Extra: dev
Requires-Dist: black>=23.0.0; extra == 'dev'
Requires-Dist: mypy>=1.0.0; extra == 'dev'
Requires-Dist: pytest>=7.0.0; extra == 'dev'
Requires-Dist: ruff>=0.1.0; extra == 'dev'
Requires-Dist: types-requests; extra == 'dev'
